{"type":"FeatureCollection", "features": [
{"type":"Feature","geometry":{"type":"Point","coordinates":[-80.4453,36.0098]},"properties":{"educationprogramcode":"US19104700"}},
{"type":"Feature","geometry":{"type":"Point","coordinates":[-80.4457,36.014]},"properties":{"educationprogramcode":"US19104700"}},
{"type":"Feature","geometry":{"type":"Point","coordinates":[-80.3993,36.0307]},"properties":{"educationprogramcode":"US19104700"}},
{"type":"Feature","geometry":{"type":"Point","coordinates":[-80.3914,36.0387]},"properties":{"educationprogramcode":"US19104700"}},
{"type":"Feature","geometry":{"type":"Point","coordinates":[-80.3991,36.0332]},"properties":{"educationprogramcode":"US19104700"}},
{"type":"Feature","geometry":{"type":"Point","coordinates":[-80.6755,35.745]},"properties":{"educationprogramcode":"US19104700"}},
{"type":"Feature","geometry":{"type":"Point","coordinates":[-80.5604,35.8103]},"properties":{"educationprogramcode":"US19104700"}},
{"type":"Feature","geometry":{"type":"Point","coordinates":[-80.4218,36.0955]},"properties":{"educationprogramcode":"US19104700"}},
{"type":"Feature","geometry":{"type":"Point","coordinates":[-80.5565,35.9046]},"properties":{"educationprogramcode":"US19104700"}},
{"type":"Feature","geometry":{"type":"Point","coordinates":[-80.5529,35.9092]},"properties":{"educationprogramcode":"US19104700"}},
{"type":"Feature","geometry":{"type":"Point","coordinates":[-80.5596,35.9048]},"properties":{"educationprogramcode":"US19104700"}},
{"type":"Feature","geometry":{"type":"Point","coordinates":[-80.5584,35.907]},"properties":{"educationprogramcode":"US19104700"}},
{"type":"Feature","geometry":{"type":"Point","coordinates":[-80.5578,35.9086]},"properties":{"educationprogramcode":"US19104700"}},
{"type":"Feature","geometry":{"type":"Point","coordinates":[-80.5574,35.9089]},"properties":{"educationprogramcode":"US19104700"}},
{"type":"Feature","geometry":{"type":"Point","coordinates":[-80.5581,35.9063]},"properties":{"educationprogramcode":"US19104700"}},
{"type":"Feature","geometry":{"type":"Point","coordinates":[-80.5534,35.9059]},"properties":{"educationprogramcode":"US19104700"}},
{"type":"Feature","geometry":{"type":"Point","coordinates":[-80.5532,35.9074]},"properties":{"educationprogramcode":"US19104700"}},
{"type":"Feature","geometry":{"type":"Point","coordinates":[-80.5589,35.9077]},"properties":{"educationprogramcode":"US19104700"}},
{"type":"Feature","geometry":{"type":"Point","coordinates":[-80.6231,36.1359]},"properties":{"educationprogramcode":"US19104700"}},
{"type":"Feature","geometry":{"type":"Point","coordinates":[-80.6213,36.1399]},"properties":{"educationprogramcode":"US19104700"}},
{"type":"Feature","geometry":{"type":"Point","coordinates":[-80.212,36.103]},"properties":{"educationprogramcode":"US19104700"}},
{"type":"Feature","geometry":{"type":"Point","coordinates":[-80.2037,36.111]},"properties":{"educationprogramcode":"US19104700"}},
{"type":"Feature","geometry":{"type":"Point","coordinates":[-80.3243,36.0812]},"properties":{"educationprogramcode":"US19104700"}},
{"type":"Feature","geometry":{"type":"Point","coordinates":[-80.3099,36.0785]},"properties":{"educationprogramcode":"US19104700"}},
{"type":"Feature","geometry":{"type":"Point","coordinates":[-80.3293,36.0695]},"properties":{"educationprogramcode":"US19104700"}},
{"type":"Feature","geometry":{"type":"Point","coordinates":[-80.3206,36.072]},"properties":{"educationprogramcode":"US19104700"}},
{"type":"Feature","geometry":{"type":"Point","coordinates":[-80.3214,36.0718]},"properties":{"educationprogramcode":"US19104700"}},
{"type":"Feature","geometry":{"type":"Point","coordinates":[-80.3257,36.0641]},"properties":{"educationprogramcode":"US19104700"}},
{"type":"Feature","geometry":{"type":"Point","coordinates":[-80.331,36.0739]},"properties":{"educationprogramcode":"US19104700"}},
{"type":"Feature","geometry":{"type":"Point","coordinates":[-80.3018,36.0818]},"properties":{"educationprogramcode":"US19104700"}},
{"type":"Feature","geometry":{"type":"Point","coordinates":[-80.3201,36.0662]},"properties":{"educationprogramcode":"US19104700"}},
{"type":"Feature","geometry":{"type":"Point","coordinates":[-80.3271,36.0616]},"properties":{"educationprogramcode":"US19104700"}},
{"type":"Feature","geometry":{"type":"Point","coordinates":[-80.3165,36.0574]},"properties":{"educationprogramcode":"US19104700"}},
{"type":"Feature","geometry":{"type":"Point","coordinates":[-80.3132,36.0688]},"properties":{"educationprogramcode":"US19104700"}},
{"type":"Feature","geometry":{"type":"Point","coordinates":[-80.3123,36.062]},"properties":{"educationprogramcode":"US19104700"}},
{"type":"Feature","geometry":{"type":"Point","coordinates":[-80.3218,36.0984]},"properties":{"educationprogramcode":"US19104700"}},
{"type":"Feature","geometry":{"type":"Point","coordinates":[-80.3255,36.0915]},"properties":{"educationprogramcode":"US19104700"}},
{"type":"Feature","geometry":{"type":"Point","coordinates":[-80.3228,36.1516]},"properties":{"educationprogramcode":"US19104700"}},
{"type":"Feature","geometry":{"type":"Point","coordinates":[-80.1839,36.0659]},"properties":{"educationprogramcode":"US19104700"}},
{"type":"Feature","geometry":{"type":"Point","coordinates":[-80.268,36.0423]},"properties":{"educationprogramcode":"US19104700"}},
{"type":"Feature","geometry":{"type":"Point","coordinates":[-80.2668,36.0428]},"properties":{"educationprogramcode":"US19104700"}},
{"type":"Feature","geometry":{"type":"Point","coordinates":[-80.2607,36.0511]},"properties":{"educationprogramcode":"US19104700"}},
{"type":"Feature","geometry":{"type":"Point","coordinates":[-80.2619,36.0452]},"properties":{"educationprogramcode":"US19104700"}},
{"type":"Feature","geometry":{"type":"Point","coordinates":[-80.3191,36.0507]},"properties":{"educationprogramcode":"US19104700"}},
{"type":"Feature","geometry":{"type":"Point","coordinates":[-79.9987,35.9683]},"properties":{"educationprogramcode":"US19104700"}},
{"type":"Feature","geometry":{"type":"Point","coordinates":[-80.0022,35.9731]},"properties":{"educationprogramcode":"US19104700"}},
{"type":"Feature","geometry":{"type":"Point","coordinates":[-80.0425,35.9584]},"properties":{"educationprogramcode":"US19104700"}},
{"type":"Feature","geometry":{"type":"Point","coordinates":[-80.034,35.9591]},"properties":{"educationprogramcode":"US19104700"}},
{"type":"Feature","geometry":{"type":"Point","coordinates":[-80.0424,35.958]},"properties":{"educationprogramcode":"US19104700"}},
{"type":"Feature","geometry":{"type":"Point","coordinates":[-80.0375,35.9509]},"properties":{"educationprogramcode":"US19104700"}},
{"type":"Feature","geometry":{"type":"Point","coordinates":[-80.0459,35.9516]},"properties":{"educationprogramcode":"US19104700"}},
{"type":"Feature","geometry":{"type":"Point","coordinates":[-79.998,36.0149]},"properties":{"educationprogramcode":"US19104700"}},
{"type":"Feature","geometry":{"type":"Point","coordinates":[-80.0033,36.006]},"properties":{"educationprogramcode":"US19104700"}},
{"type":"Feature","geometry":{"type":"Point","coordinates":[-79.9987,36.0093]},"properties":{"educationprogramcode":"US19104700"}},
{"type":"Feature","geometry":{"type":"Point","coordinates":[-80.2834,35.828]},"properties":{"educationprogramcode":"US19104700"}},
{"type":"Feature","geometry":{"type":"Point","coordinates":[-80.2746,35.8283]},"properties":{"educationprogramcode":"US19104700"}},
{"type":"Feature","geometry":{"type":"Point","coordinates":[-80.2737,35.8269]},"properties":{"educationprogramcode":"US19104700"}},
{"type":"Feature","geometry":{"type":"Point","coordinates":[-80.2816,35.8316]},"properties":{"educationprogramcode":"US19104700"}},
{"type":"Feature","geometry":{"type":"Point","coordinates":[-80.2805,35.8274]},"properties":{"educationprogramcode":"US19104700"}},
{"type":"Feature","geometry":{"type":"Point","coordinates":[-80.275,35.8233]},"properties":{"educationprogramcode":"US19104700"}},
{"type":"Feature","geometry":{"type":"Point","coordinates":[-80.2762,35.8289]},"properties":{"educationprogramcode":"US19104700"}},
{"type":"Feature","geometry":{"type":"Point","coordinates":[-80.2717,35.8198]},"properties":{"educationprogramcode":"US19104700"}},
{"type":"Feature","geometry":{"type":"Point","coordinates":[-80.2837,35.8288]},"properties":{"educationprogramcode":"US19104700"}},
{"type":"Feature","geometry":{"type":"Point","coordinates":[-80.2829,35.8278]},"properties":{"educationprogramcode":"US19104700"}},
{"type":"Feature","geometry":{"type":"Point","coordinates":[-80.28,35.8301]},"properties":{"educationprogramcode":"US19104700"}},
{"type":"Feature","geometry":{"type":"Point","coordinates":[-80.2727,35.8223]},"properties":{"educationprogramcode":"US19104700"}},
{"type":"Feature","geometry":{"type":"Point","coordinates":[-80.2801,35.8262]},"properties":{"educationprogramcode":"US19104700"}},
{"type":"Feature","geometry":{"type":"Point","coordinates":[-80.2789,35.8201]},"properties":{"educationprogramcode":"US19104700"}},
{"type":"Feature","geometry":{"type":"Point","coordinates":[-80.2838,35.8232]},"properties":{"educationprogramcode":"US19104700"}},
{"type":"Feature","geometry":{"type":"Point","coordinates":[-80.2759,35.8287]},"properties":{"educationprogramcode":"US19104700"}},
{"type":"Feature","geometry":{"type":"Point","coordinates":[-80.273,35.8276]},"properties":{"educationprogramcode":"US19104700"}},
{"type":"Feature","geometry":{"type":"Point","coordinates":[-80.262,35.8125]},"properties":{"educationprogramcode":"US19104700"}},
{"type":"Feature","geometry":{"type":"Point","coordinates":[-80.2535,35.8121]},"properties":{"educationprogramcode":"US19104700"}},
{"type":"Feature","geometry":{"type":"Point","coordinates":[-80.2552,35.8147]},"properties":{"educationprogramcode":"US19104700"}},
{"type":"Feature","geometry":{"type":"Point","coordinates":[-80.2575,35.8122]},"properties":{"educationprogramcode":"US19104700"}},
{"type":"Feature","geometry":{"type":"Point","coordinates":[-80.26,35.8068]},"properties":{"educationprogramcode":"US19104700"}},
{"type":"Feature","geometry":{"type":"Point","coordinates":[-80.2589,35.8117]},"properties":{"educationprogramcode":"US19104700"}},
{"type":"Feature","geometry":{"type":"Point","coordinates":[-80.2578,35.8148]},"properties":{"educationprogramcode":"US19104700"}},
{"type":"Feature","geometry":{"type":"Point","coordinates":[-80.2609,35.8144]},"properties":{"educationprogramcode":"US19104700"}},
{"type":"Feature","geometry":{"type":"Point","coordinates":[-80.253,35.8081]},"properties":{"educationprogramcode":"US19104700"}},
{"type":"Feature","geometry":{"type":"Point","coordinates":[-79.7593,35.9506]},"properties":{"educationprogramcode":"US19104700"}},
{"type":"Feature","geometry":{"type":"Point","coordinates":[-79.623,35.7047]},"properties":{"educationprogramcode":"US19104700"}},
{"type":"Feature","geometry":{"type":"Point","coordinates":[-80.0821,35.8782]},"properties":{"educationprogramcode":"US19104700"}},
{"type":"Feature","geometry":{"type":"Point","coordinates":[-80.0847,35.8748]},"properties":{"educationprogramcode":"US19104700"}},
{"type":"Feature","geometry":{"type":"Point","coordinates":[-80.0893,35.8773]},"properties":{"educationprogramcode":"US19104700"}},
{"type":"Feature","geometry":{"type":"Point","coordinates":[-80.0786,35.8865]},"properties":{"educationprogramcode":"US19104700"}},
{"type":"Feature","geometry":{"type":"Point","coordinates":[-80.0773,35.8815]},"properties":{"educationprogramcode":"US19104700"}},
{"type":"Feature","geometry":{"type":"Point","coordinates":[-80.0802,35.8849]},"properties":{"educationprogramcode":"US19104700"}},
{"type":"Feature","geometry":{"type":"Point","coordinates":[-80.0762,35.8764]},"properties":{"educationprogramcode":"US19104700"}},
{"type":"Feature","geometry":{"type":"Point","coordinates":[-80.0794,35.8834]},"properties":{"educationprogramcode":"US19104700"}},
{"type":"Feature","geometry":{"type":"Point","coordinates":[-80.0884,35.8811]},"properties":{"educationprogramcode":"US19104700"}},
{"type":"Feature","geometry":{"type":"Point","coordinates":[-80.0818,35.8815]},"properties":{"educationprogramcode":"US19104700"}},
{"type":"Feature","geometry":{"type":"Point","coordinates":[-80.078,35.8825]},"properties":{"educationprogramcode":"US19104700"}},
{"type":"Feature","geometry":{"type":"Point","coordinates":[-80.0856,35.8841]},"properties":{"educationprogramcode":"US19104700"}},
{"type":"Feature","geometry":{"type":"Point","coordinates":[-80.0776,35.8764]},"properties":{"educationprogramcode":"US19104700"}},
{"type":"Feature","geometry":{"type":"Point","coordinates":[-80.0778,35.8812]},"properties":{"educationprogramcode":"US19104700"}},
{"type":"Feature","geometry":{"type":"Point","coordinates":[-80.0821,35.882]},"properties":{"educationprogramcode":"US19104700"}},
{"type":"Feature","geometry":{"type":"Point","coordinates":[-80.0856,35.8809]},"properties":{"educationprogramcode":"US19104700"}},
{"type":"Feature","geometry":{"type":"Point","coordinates":[-80.0867,35.8754]},"properties":{"educationprogramcode":"US19104700"}},
{"type":"Feature","geometry":{"type":"Point","coordinates":[-80.0815,35.8825]},"properties":{"educationprogramcode":"US19104700"}},
{"type":"Feature","geometry":{"type":"Point","coordinates":[-80.1007,35.8751]},"properties":{"educationprogramcode":"US19104700"}},
{"type":"Feature","geometry":{"type":"Point","coordinates":[-79.8609,35.3658]},"properties":{"educationprogramcode":"US19104700"}},
{"type":"Feature","geometry":{"type":"Point","coordinates":[-79.8755,36.0121]},"properties":{"educationprogramcode":"US19104700"}},
{"type":"Feature","geometry":{"type":"Point","coordinates":[-79.9303,36.0966]},"properties":{"educationprogramcode":"US19104700"}},
{"type":"Feature","geometry":{"type":"Point","coordinates":[-78.9478,36.0139]},"properties":{"educationprogramcode":"US19104700"}},
{"type":"Feature","geometry":{"type":"Point","coordinates":[-80.6464,35.4145]},"properties":{"educationprogramcode":"US19104700"}},
{"type":"Feature","geometry":{"type":"Point","coordinates":[-80.3232,35.4827]},"properties":{"educationprogramcode":"US19104700"}},
{"type":"Feature","geometry":{"type":"Point","coordinates":[-80.4809,35.6708]},"properties":{"educationprogramcode":"US19104700"}},
{"type":"Feature","geometry":{"type":"Point","coordinates":[-80.479,35.6624]},"properties":{"educationprogramcode":"US19104700"}},
{"type":"Feature","geometry":{"type":"Point","coordinates":[-80.48,35.6691]},"properties":{"educationprogramcode":"US19104700"}},
{"type":"Feature","geometry":{"type":"Point","coordinates":[-80.5352,35.6653]},"properties":{"educationprogramcode":"US19104700"}},
{"type":"Feature","geometry":{"type":"Point","coordinates":[-80.5298,35.6686]},"properties":{"educationprogramcode":"US19104700"}},
{"type":"Feature","geometry":{"type":"Point","coordinates":[-80.877,35.2883]},"properties":{"educationprogramcode":"US19104700"}},
{"type":"Feature","geometry":{"type":"Point","coordinates":[-80.8907,35.7776]},"properties":{"educationprogramcode":"US19104700"}},
{"type":"Feature","geometry":{"type":"Point","coordinates":[-81.7113,35.7411]},"properties":{"educationprogramcode":"US19104700"}},
{"type":"Feature","geometry":{"type":"Point","coordinates":[-80.8945,35.8506]},"properties":{"educationprogramcode":"US19104700"}}
]}