{"type":"FeatureCollection", "features": [
{"type":"Feature","geometry":{"type":"Point","coordinates":[-80.31617,36.069214]},"properties":{"educationprogramcode":"US19402600"}},
{"type":"Feature","geometry":{"type":"Point","coordinates":[-79.168611,35.459277]},"properties":{"educationprogramcode":"US19402600"}},
{"type":"Feature","geometry":{"type":"Point","coordinates":[-79.817365,36.106359]},"properties":{"educationprogramcode":"US19402600"}},
{"type":"Feature","geometry":{"type":"Point","coordinates":[-79.817365,36.106359]},"properties":{"educationprogramcode":"US19402600"}},
{"type":"Feature","geometry":{"type":"Point","coordinates":[-78.742398,35.510553]},"properties":{"educationprogramcode":"US19402600"}},
{"type":"Feature","geometry":{"type":"Point","coordinates":[-78.742398,35.510553]},"properties":{"educationprogramcode":"US19402600"}},
{"type":"Feature","geometry":{"type":"Point","coordinates":[-78.742398,35.510553]},"properties":{"educationprogramcode":"US19402600"}},
{"type":"Feature","geometry":{"type":"Point","coordinates":[-78.742398,35.510553]},"properties":{"educationprogramcode":"US19402600"}},
{"type":"Feature","geometry":{"type":"Point","coordinates":[-78.81965,35.711653]},"properties":{"educationprogramcode":"US19402600"}},
{"type":"Feature","geometry":{"type":"Point","coordinates":[-78.81965,35.711653]},"properties":{"educationprogramcode":"US19402600"}},
{"type":"Feature","geometry":{"type":"Point","coordinates":[-78.81965,35.711653]},"properties":{"educationprogramcode":"US19402600"}},
{"type":"Feature","geometry":{"type":"Point","coordinates":[-78.81965,35.711653]},"properties":{"educationprogramcode":"US19402600"}},
{"type":"Feature","geometry":{"type":"Point","coordinates":[-78.81965,35.711653]},"properties":{"educationprogramcode":"US19402600"}},
{"type":"Feature","geometry":{"type":"Point","coordinates":[-78.54782,35.39415]},"properties":{"educationprogramcode":"US19402600"}},
{"type":"Feature","geometry":{"type":"Point","coordinates":[-78.54782,35.39415]},"properties":{"educationprogramcode":"US19402600"}},
{"type":"Feature","geometry":{"type":"Point","coordinates":[-78.54782,35.39415]},"properties":{"educationprogramcode":"US19402600"}},
{"type":"Feature","geometry":{"type":"Point","coordinates":[-78.54782,35.39415]},"properties":{"educationprogramcode":"US19402600"}},
{"type":"Feature","geometry":{"type":"Point","coordinates":[-78.54782,35.39415]},"properties":{"educationprogramcode":"US19402600"}},
{"type":"Feature","geometry":{"type":"Point","coordinates":[-78.54782,35.39415]},"properties":{"educationprogramcode":"US19402600"}},
{"type":"Feature","geometry":{"type":"Point","coordinates":[-78.54782,35.39415]},"properties":{"educationprogramcode":"US19402600"}},
{"type":"Feature","geometry":{"type":"Point","coordinates":[-78.54782,35.39415]},"properties":{"educationprogramcode":"US19402600"}},
{"type":"Feature","geometry":{"type":"Point","coordinates":[-78.54782,35.39415]},"properties":{"educationprogramcode":"US19402600"}},
{"type":"Feature","geometry":{"type":"Point","coordinates":[-78.54782,35.39415]},"properties":{"educationprogramcode":"US19402600"}},
{"type":"Feature","geometry":{"type":"Point","coordinates":[-78.54782,35.39415]},"properties":{"educationprogramcode":"US19402600"}},
{"type":"Feature","geometry":{"type":"Point","coordinates":[-78.54782,35.39415]},"properties":{"educationprogramcode":"US19402600"}},
{"type":"Feature","geometry":{"type":"Point","coordinates":[-78.797679,35.80541]},"properties":{"educationprogramcode":"US19402600"}},
{"type":"Feature","geometry":{"type":"Point","coordinates":[-78.797679,35.80541]},"properties":{"educationprogramcode":"US19402600"}},
{"type":"Feature","geometry":{"type":"Point","coordinates":[-78.797679,35.80541]},"properties":{"educationprogramcode":"US19402600"}},
{"type":"Feature","geometry":{"type":"Point","coordinates":[-79.037474,35.934949]},"properties":{"educationprogramcode":"US19402600"}},
{"type":"Feature","geometry":{"type":"Point","coordinates":[-79.040688,35.938902]},"properties":{"educationprogramcode":"US19402600"}},
{"type":"Feature","geometry":{"type":"Point","coordinates":[-78.78153,35.756619]},"properties":{"educationprogramcode":"US19402600"}},
{"type":"Feature","geometry":{"type":"Point","coordinates":[-78.78153,35.756619]},"properties":{"educationprogramcode":"US19402600"}},
{"type":"Feature","geometry":{"type":"Point","coordinates":[-78.78153,35.756619]},"properties":{"educationprogramcode":"US19402600"}},
{"type":"Feature","geometry":{"type":"Point","coordinates":[-78.78153,35.756619]},"properties":{"educationprogramcode":"US19402600"}},
{"type":"Feature","geometry":{"type":"Point","coordinates":[-78.78153,35.756619]},"properties":{"educationprogramcode":"US19402600"}},
{"type":"Feature","geometry":{"type":"Point","coordinates":[-78.78153,35.756619]},"properties":{"educationprogramcode":"US19402600"}},
{"type":"Feature","geometry":{"type":"Point","coordinates":[-78.444815,35.636282]},"properties":{"educationprogramcode":"US19402600"}},
{"type":"Feature","geometry":{"type":"Point","coordinates":[-78.444815,35.636282]},"properties":{"educationprogramcode":"US19402600"}},
{"type":"Feature","geometry":{"type":"Point","coordinates":[-78.444815,35.636282]},"properties":{"educationprogramcode":"US19402600"}},
{"type":"Feature","geometry":{"type":"Point","coordinates":[-78.444815,35.636282]},"properties":{"educationprogramcode":"US19402600"}},
{"type":"Feature","geometry":{"type":"Point","coordinates":[-78.444815,35.636282]},"properties":{"educationprogramcode":"US19402600"}},
{"type":"Feature","geometry":{"type":"Point","coordinates":[-78.444815,35.636282]},"properties":{"educationprogramcode":"US19402600"}},
{"type":"Feature","geometry":{"type":"Point","coordinates":[-78.444815,35.636282]},"properties":{"educationprogramcode":"US19402600"}},
{"type":"Feature","geometry":{"type":"Point","coordinates":[-78.444815,35.636282]},"properties":{"educationprogramcode":"US19402600"}},
{"type":"Feature","geometry":{"type":"Point","coordinates":[-78.444815,35.636282]},"properties":{"educationprogramcode":"US19402600"}},
{"type":"Feature","geometry":{"type":"Point","coordinates":[-78.444815,35.636282]},"properties":{"educationprogramcode":"US19402600"}},
{"type":"Feature","geometry":{"type":"Point","coordinates":[-78.444815,35.636282]},"properties":{"educationprogramcode":"US19402600"}},
{"type":"Feature","geometry":{"type":"Point","coordinates":[-78.444815,35.636282]},"properties":{"educationprogramcode":"US19402600"}},
{"type":"Feature","geometry":{"type":"Point","coordinates":[-78.444815,35.636282]},"properties":{"educationprogramcode":"US19402600"}},
{"type":"Feature","geometry":{"type":"Point","coordinates":[-78.444815,35.636282]},"properties":{"educationprogramcode":"US19402600"}},
{"type":"Feature","geometry":{"type":"Point","coordinates":[-78.444815,35.636282]},"properties":{"educationprogramcode":"US19402600"}},
{"type":"Feature","geometry":{"type":"Point","coordinates":[-78.444815,35.636282]},"properties":{"educationprogramcode":"US19402600"}},
{"type":"Feature","geometry":{"type":"Point","coordinates":[-78.444815,35.636282]},"properties":{"educationprogramcode":"US19402600"}},
{"type":"Feature","geometry":{"type":"Point","coordinates":[-78.444815,35.636282]},"properties":{"educationprogramcode":"US19402600"}},
{"type":"Feature","geometry":{"type":"Point","coordinates":[-78.444815,35.636282]},"properties":{"educationprogramcode":"US19402600"}},
{"type":"Feature","geometry":{"type":"Point","coordinates":[-78.444815,35.636282]},"properties":{"educationprogramcode":"US19402600"}},
{"type":"Feature","geometry":{"type":"Point","coordinates":[-78.444815,35.636282]},"properties":{"educationprogramcode":"US19402600"}},
{"type":"Feature","geometry":{"type":"Point","coordinates":[-78.444815,35.636282]},"properties":{"educationprogramcode":"US19402600"}},
{"type":"Feature","geometry":{"type":"Point","coordinates":[-78.444815,35.636282]},"properties":{"educationprogramcode":"US19402600"}},
{"type":"Feature","geometry":{"type":"Point","coordinates":[-78.444815,35.636282]},"properties":{"educationprogramcode":"US19402600"}},
{"type":"Feature","geometry":{"type":"Point","coordinates":[-78.444815,35.636282]},"properties":{"educationprogramcode":"US19402600"}},
{"type":"Feature","geometry":{"type":"Point","coordinates":[-78.444815,35.636282]},"properties":{"educationprogramcode":"US19402600"}},
{"type":"Feature","geometry":{"type":"Point","coordinates":[-78.444815,35.636282]},"properties":{"educationprogramcode":"US19402600"}},
{"type":"Feature","geometry":{"type":"Point","coordinates":[-78.444815,35.636282]},"properties":{"educationprogramcode":"US19402600"}},
{"type":"Feature","geometry":{"type":"Point","coordinates":[-78.444815,35.636282]},"properties":{"educationprogramcode":"US19402600"}},
{"type":"Feature","geometry":{"type":"Point","coordinates":[-78.444815,35.636282]},"properties":{"educationprogramcode":"US19402600"}},
{"type":"Feature","geometry":{"type":"Point","coordinates":[-78.444815,35.636282]},"properties":{"educationprogramcode":"US19402600"}},
{"type":"Feature","geometry":{"type":"Point","coordinates":[-78.672574,35.410283]},"properties":{"educationprogramcode":"US19402600"}},
{"type":"Feature","geometry":{"type":"Point","coordinates":[-78.672574,35.410283]},"properties":{"educationprogramcode":"US19402600"}},
{"type":"Feature","geometry":{"type":"Point","coordinates":[-78.672574,35.410283]},"properties":{"educationprogramcode":"US19402600"}},
{"type":"Feature","geometry":{"type":"Point","coordinates":[-78.425508,35.448202]},"properties":{"educationprogramcode":"US19402600"}},
{"type":"Feature","geometry":{"type":"Point","coordinates":[-78.425508,35.448202]},"properties":{"educationprogramcode":"US19402600"}},
{"type":"Feature","geometry":{"type":"Point","coordinates":[-78.425508,35.448202]},"properties":{"educationprogramcode":"US19402600"}},
{"type":"Feature","geometry":{"type":"Point","coordinates":[-78.452456,36.096252]},"properties":{"educationprogramcode":"US19402600"}},
{"type":"Feature","geometry":{"type":"Point","coordinates":[-78.78432,35.59854]},"properties":{"educationprogramcode":"US19402600"}},
{"type":"Feature","geometry":{"type":"Point","coordinates":[-78.78432,35.59854]},"properties":{"educationprogramcode":"US19402600"}},
{"type":"Feature","geometry":{"type":"Point","coordinates":[-78.78432,35.59854]},"properties":{"educationprogramcode":"US19402600"}},
{"type":"Feature","geometry":{"type":"Point","coordinates":[-78.78432,35.59854]},"properties":{"educationprogramcode":"US19402600"}},
{"type":"Feature","geometry":{"type":"Point","coordinates":[-78.78432,35.59854]},"properties":{"educationprogramcode":"US19402600"}},
{"type":"Feature","geometry":{"type":"Point","coordinates":[-78.456667,35.650556]},"properties":{"educationprogramcode":"US19402600"}},
{"type":"Feature","geometry":{"type":"Point","coordinates":[-78.456667,35.650556]},"properties":{"educationprogramcode":"US19402600"}},
{"type":"Feature","geometry":{"type":"Point","coordinates":[-78.456667,35.650556]},"properties":{"educationprogramcode":"US19402600"}},
{"type":"Feature","geometry":{"type":"Point","coordinates":[-78.456667,35.650556]},"properties":{"educationprogramcode":"US19402600"}},
{"type":"Feature","geometry":{"type":"Point","coordinates":[-78.456667,35.650556]},"properties":{"educationprogramcode":"US19402600"}},
{"type":"Feature","geometry":{"type":"Point","coordinates":[-78.456667,35.650556]},"properties":{"educationprogramcode":"US19402600"}},
{"type":"Feature","geometry":{"type":"Point","coordinates":[-78.456667,35.650556]},"properties":{"educationprogramcode":"US19402600"}},
{"type":"Feature","geometry":{"type":"Point","coordinates":[-78.456667,35.650556]},"properties":{"educationprogramcode":"US19402600"}},
{"type":"Feature","geometry":{"type":"Point","coordinates":[-78.456667,35.650556]},"properties":{"educationprogramcode":"US19402600"}},
{"type":"Feature","geometry":{"type":"Point","coordinates":[-78.456667,35.650556]},"properties":{"educationprogramcode":"US19402600"}},
{"type":"Feature","geometry":{"type":"Point","coordinates":[-78.456667,35.650556]},"properties":{"educationprogramcode":"US19402600"}},
{"type":"Feature","geometry":{"type":"Point","coordinates":[-78.456667,35.650556]},"properties":{"educationprogramcode":"US19402600"}},
{"type":"Feature","geometry":{"type":"Point","coordinates":[-78.456667,35.650556]},"properties":{"educationprogramcode":"US19402600"}},
{"type":"Feature","geometry":{"type":"Point","coordinates":[-78.456667,35.650556]},"properties":{"educationprogramcode":"US19402600"}},
{"type":"Feature","geometry":{"type":"Point","coordinates":[-78.60826,35.684813]},"properties":{"educationprogramcode":"US19402600"}},
{"type":"Feature","geometry":{"type":"Point","coordinates":[-78.60826,35.684813]},"properties":{"educationprogramcode":"US19402600"}},
{"type":"Feature","geometry":{"type":"Point","coordinates":[-78.60826,35.684813]},"properties":{"educationprogramcode":"US19402600"}},
{"type":"Feature","geometry":{"type":"Point","coordinates":[-78.60826,35.684813]},"properties":{"educationprogramcode":"US19402600"}},
{"type":"Feature","geometry":{"type":"Point","coordinates":[-78.60826,35.684813]},"properties":{"educationprogramcode":"US19402600"}},
{"type":"Feature","geometry":{"type":"Point","coordinates":[-78.60826,35.684813]},"properties":{"educationprogramcode":"US19402600"}},
{"type":"Feature","geometry":{"type":"Point","coordinates":[-78.60826,35.684813]},"properties":{"educationprogramcode":"US19402600"}},
{"type":"Feature","geometry":{"type":"Point","coordinates":[-78.60826,35.684813]},"properties":{"educationprogramcode":"US19402600"}},
{"type":"Feature","geometry":{"type":"Point","coordinates":[-78.60826,35.684813]},"properties":{"educationprogramcode":"US19402600"}},
{"type":"Feature","geometry":{"type":"Point","coordinates":[-78.60826,35.684813]},"properties":{"educationprogramcode":"US19402600"}},
{"type":"Feature","geometry":{"type":"Point","coordinates":[-78.60826,35.684813]},"properties":{"educationprogramcode":"US19402600"}},
{"type":"Feature","geometry":{"type":"Point","coordinates":[-78.60826,35.684813]},"properties":{"educationprogramcode":"US19402600"}},
{"type":"Feature","geometry":{"type":"Point","coordinates":[-78.60826,35.684813]},"properties":{"educationprogramcode":"US19402600"}},
{"type":"Feature","geometry":{"type":"Point","coordinates":[-78.60826,35.684813]},"properties":{"educationprogramcode":"US19402600"}},
{"type":"Feature","geometry":{"type":"Point","coordinates":[-78.60826,35.684813]},"properties":{"educationprogramcode":"US19402600"}},
{"type":"Feature","geometry":{"type":"Point","coordinates":[-78.60826,35.684813]},"properties":{"educationprogramcode":"US19402600"}},
{"type":"Feature","geometry":{"type":"Point","coordinates":[-78.60826,35.684813]},"properties":{"educationprogramcode":"US19402600"}},
{"type":"Feature","geometry":{"type":"Point","coordinates":[-78.09786,35.37996]},"properties":{"educationprogramcode":"US19402600"}},
{"type":"Feature","geometry":{"type":"Point","coordinates":[-78.09786,35.37996]},"properties":{"educationprogramcode":"US19402600"}},
{"type":"Feature","geometry":{"type":"Point","coordinates":[-78.09786,35.37996]},"properties":{"educationprogramcode":"US19402600"}},
{"type":"Feature","geometry":{"type":"Point","coordinates":[-78.09786,35.37996]},"properties":{"educationprogramcode":"US19402600"}},
{"type":"Feature","geometry":{"type":"Point","coordinates":[-78.09786,35.37996]},"properties":{"educationprogramcode":"US19402600"}},
{"type":"Feature","geometry":{"type":"Point","coordinates":[-78.09786,35.37996]},"properties":{"educationprogramcode":"US19402600"}},
{"type":"Feature","geometry":{"type":"Point","coordinates":[-78.09786,35.37996]},"properties":{"educationprogramcode":"US19402600"}},
{"type":"Feature","geometry":{"type":"Point","coordinates":[-77.930853,35.370546]},"properties":{"educationprogramcode":"US19402600"}},
{"type":"Feature","geometry":{"type":"Point","coordinates":[-77.930853,35.370546]},"properties":{"educationprogramcode":"US19402600"}},
{"type":"Feature","geometry":{"type":"Point","coordinates":[-77.930853,35.370546]},"properties":{"educationprogramcode":"US19402600"}},
{"type":"Feature","geometry":{"type":"Point","coordinates":[-77.930853,35.370546]},"properties":{"educationprogramcode":"US19402600"}},
{"type":"Feature","geometry":{"type":"Point","coordinates":[-78.834978,35.623511]},"properties":{"educationprogramcode":"US19402600"}},
{"type":"Feature","geometry":{"type":"Point","coordinates":[-78.122283,35.590858]},"properties":{"educationprogramcode":"US19402600"}},
{"type":"Feature","geometry":{"type":"Point","coordinates":[-78.122283,35.590858]},"properties":{"educationprogramcode":"US19402600"}},
{"type":"Feature","geometry":{"type":"Point","coordinates":[-78.122283,35.590858]},"properties":{"educationprogramcode":"US19402600"}},
{"type":"Feature","geometry":{"type":"Point","coordinates":[-78.122283,35.590858]},"properties":{"educationprogramcode":"US19402600"}},
{"type":"Feature","geometry":{"type":"Point","coordinates":[-78.483413,35.787687]},"properties":{"educationprogramcode":"US19402600"}},
{"type":"Feature","geometry":{"type":"Point","coordinates":[-78.483413,35.787687]},"properties":{"educationprogramcode":"US19402600"}},
{"type":"Feature","geometry":{"type":"Point","coordinates":[-78.483413,35.787687]},"properties":{"educationprogramcode":"US19402600"}},
{"type":"Feature","geometry":{"type":"Point","coordinates":[-78.813484,35.397219]},"properties":{"educationprogramcode":"US19402600"}},
{"type":"Feature","geometry":{"type":"Point","coordinates":[-78.813484,35.397219]},"properties":{"educationprogramcode":"US19402600"}},
{"type":"Feature","geometry":{"type":"Point","coordinates":[-78.299777,36.089778]},"properties":{"educationprogramcode":"US19402600"}},
{"type":"Feature","geometry":{"type":"Point","coordinates":[-78.934329,35.42006]},"properties":{"educationprogramcode":"US19402600"}},
{"type":"Feature","geometry":{"type":"Point","coordinates":[-78.29238,36.46878]},"properties":{"educationprogramcode":"US19402600"}},
{"type":"Feature","geometry":{"type":"Point","coordinates":[-78.189798,35.791243]},"properties":{"educationprogramcode":"US19402600"}},
{"type":"Feature","geometry":{"type":"Point","coordinates":[-78.836037,35.825795]},"properties":{"educationprogramcode":"US19402600"}},
{"type":"Feature","geometry":{"type":"Point","coordinates":[-78.162907,35.464515]},"properties":{"educationprogramcode":"US19402600"}},
{"type":"Feature","geometry":{"type":"Point","coordinates":[-78.162907,35.464515]},"properties":{"educationprogramcode":"US19402600"}},
{"type":"Feature","geometry":{"type":"Point","coordinates":[-78.162907,35.464515]},"properties":{"educationprogramcode":"US19402600"}},
{"type":"Feature","geometry":{"type":"Point","coordinates":[-78.162907,35.464515]},"properties":{"educationprogramcode":"US19402600"}},
{"type":"Feature","geometry":{"type":"Point","coordinates":[-78.162907,35.464515]},"properties":{"educationprogramcode":"US19402600"}},
{"type":"Feature","geometry":{"type":"Point","coordinates":[-78.162907,35.464515]},"properties":{"educationprogramcode":"US19402600"}},
{"type":"Feature","geometry":{"type":"Point","coordinates":[-78.162907,35.464515]},"properties":{"educationprogramcode":"US19402600"}},
{"type":"Feature","geometry":{"type":"Point","coordinates":[-78.162907,35.464515]},"properties":{"educationprogramcode":"US19402600"}},
{"type":"Feature","geometry":{"type":"Point","coordinates":[-78.284629,35.541368]},"properties":{"educationprogramcode":"US19402600"}},
{"type":"Feature","geometry":{"type":"Point","coordinates":[-78.284629,35.541368]},"properties":{"educationprogramcode":"US19402600"}},
{"type":"Feature","geometry":{"type":"Point","coordinates":[-78.347308,35.512172]},"properties":{"educationprogramcode":"US19402600"}},
{"type":"Feature","geometry":{"type":"Point","coordinates":[-78.347308,35.512172]},"properties":{"educationprogramcode":"US19402600"}},
{"type":"Feature","geometry":{"type":"Point","coordinates":[-78.347308,35.512172]},"properties":{"educationprogramcode":"US19402600"}},
{"type":"Feature","geometry":{"type":"Point","coordinates":[-78.347308,35.512172]},"properties":{"educationprogramcode":"US19402600"}},
{"type":"Feature","geometry":{"type":"Point","coordinates":[-78.347308,35.512172]},"properties":{"educationprogramcode":"US19402600"}},
{"type":"Feature","geometry":{"type":"Point","coordinates":[-78.347308,35.512172]},"properties":{"educationprogramcode":"US19402600"}},
{"type":"Feature","geometry":{"type":"Point","coordinates":[-78.347308,35.512172]},"properties":{"educationprogramcode":"US19402600"}},
{"type":"Feature","geometry":{"type":"Point","coordinates":[-78.347308,35.512172]},"properties":{"educationprogramcode":"US19402600"}},
{"type":"Feature","geometry":{"type":"Point","coordinates":[-78.347308,35.512172]},"properties":{"educationprogramcode":"US19402600"}},
{"type":"Feature","geometry":{"type":"Point","coordinates":[-78.347308,35.512172]},"properties":{"educationprogramcode":"US19402600"}},
{"type":"Feature","geometry":{"type":"Point","coordinates":[-78.347308,35.512172]},"properties":{"educationprogramcode":"US19402600"}},
{"type":"Feature","geometry":{"type":"Point","coordinates":[-78.347308,35.512172]},"properties":{"educationprogramcode":"US19402600"}},
{"type":"Feature","geometry":{"type":"Point","coordinates":[-78.347308,35.512172]},"properties":{"educationprogramcode":"US19402600"}},
{"type":"Feature","geometry":{"type":"Point","coordinates":[-78.347308,35.512172]},"properties":{"educationprogramcode":"US19402600"}},
{"type":"Feature","geometry":{"type":"Point","coordinates":[-78.347308,35.512172]},"properties":{"educationprogramcode":"US19402600"}},
{"type":"Feature","geometry":{"type":"Point","coordinates":[-78.347308,35.512172]},"properties":{"educationprogramcode":"US19402600"}},
{"type":"Feature","geometry":{"type":"Point","coordinates":[-78.347308,35.512172]},"properties":{"educationprogramcode":"US19402600"}},
{"type":"Feature","geometry":{"type":"Point","coordinates":[-78.347308,35.512172]},"properties":{"educationprogramcode":"US19402600"}},
{"type":"Feature","geometry":{"type":"Point","coordinates":[-78.347308,35.512172]},"properties":{"educationprogramcode":"US19402600"}},
{"type":"Feature","geometry":{"type":"Point","coordinates":[-78.347308,35.512172]},"properties":{"educationprogramcode":"US19402600"}},
{"type":"Feature","geometry":{"type":"Point","coordinates":[-78.347308,35.512172]},"properties":{"educationprogramcode":"US19402600"}},
{"type":"Feature","geometry":{"type":"Point","coordinates":[-78.347308,35.512172]},"properties":{"educationprogramcode":"US19402600"}},
{"type":"Feature","geometry":{"type":"Point","coordinates":[-78.347308,35.512172]},"properties":{"educationprogramcode":"US19402600"}},
{"type":"Feature","geometry":{"type":"Point","coordinates":[-78.347308,35.512172]},"properties":{"educationprogramcode":"US19402600"}},
{"type":"Feature","geometry":{"type":"Point","coordinates":[-78.347308,35.512172]},"properties":{"educationprogramcode":"US19402600"}},
{"type":"Feature","geometry":{"type":"Point","coordinates":[-78.347308,35.512172]},"properties":{"educationprogramcode":"US19402600"}},
{"type":"Feature","geometry":{"type":"Point","coordinates":[-78.347308,35.512172]},"properties":{"educationprogramcode":"US19402600"}},
{"type":"Feature","geometry":{"type":"Point","coordinates":[-78.347308,35.512172]},"properties":{"educationprogramcode":"US19402600"}},
{"type":"Feature","geometry":{"type":"Point","coordinates":[-78.347308,35.512172]},"properties":{"educationprogramcode":"US19402600"}},
{"type":"Feature","geometry":{"type":"Point","coordinates":[-78.347308,35.512172]},"properties":{"educationprogramcode":"US19402600"}},
{"type":"Feature","geometry":{"type":"Point","coordinates":[-78.347308,35.512172]},"properties":{"educationprogramcode":"US19402600"}},
{"type":"Feature","geometry":{"type":"Point","coordinates":[-78.347308,35.512172]},"properties":{"educationprogramcode":"US19402600"}},
{"type":"Feature","geometry":{"type":"Point","coordinates":[-78.347308,35.512172]},"properties":{"educationprogramcode":"US19402600"}},
{"type":"Feature","geometry":{"type":"Point","coordinates":[-78.347308,35.512172]},"properties":{"educationprogramcode":"US19402600"}},
{"type":"Feature","geometry":{"type":"Point","coordinates":[-78.347308,35.512172]},"properties":{"educationprogramcode":"US19402600"}},
{"type":"Feature","geometry":{"type":"Point","coordinates":[-78.347308,35.512172]},"properties":{"educationprogramcode":"US19402600"}},
{"type":"Feature","geometry":{"type":"Point","coordinates":[-78.347308,35.512172]},"properties":{"educationprogramcode":"US19402600"}},
{"type":"Feature","geometry":{"type":"Point","coordinates":[-78.347308,35.512172]},"properties":{"educationprogramcode":"US19402600"}},
{"type":"Feature","geometry":{"type":"Point","coordinates":[-78.347308,35.512172]},"properties":{"educationprogramcode":"US19402600"}},
{"type":"Feature","geometry":{"type":"Point","coordinates":[-78.347308,35.512172]},"properties":{"educationprogramcode":"US19402600"}},
{"type":"Feature","geometry":{"type":"Point","coordinates":[-78.347308,35.512172]},"properties":{"educationprogramcode":"US19402600"}},
{"type":"Feature","geometry":{"type":"Point","coordinates":[-78.347308,35.512172]},"properties":{"educationprogramcode":"US19402600"}},
{"type":"Feature","geometry":{"type":"Point","coordinates":[-78.347308,35.512172]},"properties":{"educationprogramcode":"US19402600"}},
{"type":"Feature","geometry":{"type":"Point","coordinates":[-78.347308,35.512172]},"properties":{"educationprogramcode":"US19402600"}},
{"type":"Feature","geometry":{"type":"Point","coordinates":[-78.347308,35.512172]},"properties":{"educationprogramcode":"US19402600"}},
{"type":"Feature","geometry":{"type":"Point","coordinates":[-78.347308,35.512172]},"properties":{"educationprogramcode":"US19402600"}},
{"type":"Feature","geometry":{"type":"Point","coordinates":[-78.347308,35.512172]},"properties":{"educationprogramcode":"US19402600"}},
{"type":"Feature","geometry":{"type":"Point","coordinates":[-78.51658,35.963417]},"properties":{"educationprogramcode":"US19402600"}},
{"type":"Feature","geometry":{"type":"Point","coordinates":[-78.51658,35.963417]},"properties":{"educationprogramcode":"US19402600"}},
{"type":"Feature","geometry":{"type":"Point","coordinates":[-78.51658,35.963417]},"properties":{"educationprogramcode":"US19402600"}},
{"type":"Feature","geometry":{"type":"Point","coordinates":[-78.387755,35.792984]},"properties":{"educationprogramcode":"US19402600"}},
{"type":"Feature","geometry":{"type":"Point","coordinates":[-78.387755,35.792984]},"properties":{"educationprogramcode":"US19402600"}},
{"type":"Feature","geometry":{"type":"Point","coordinates":[-78.387755,35.792984]},"properties":{"educationprogramcode":"US19402600"}},
{"type":"Feature","geometry":{"type":"Point","coordinates":[-78.70681,35.568335]},"properties":{"educationprogramcode":"US19402600"}},
{"type":"Feature","geometry":{"type":"Point","coordinates":[-78.467462,36.025816]},"properties":{"educationprogramcode":"US19402600"}},
{"type":"Feature","geometry":{"type":"Point","coordinates":[-78.338439,35.845905]},"properties":{"educationprogramcode":"US19402600"}},
{"type":"Feature","geometry":{"type":"Point","coordinates":[-78.635142,35.772749]},"properties":{"educationprogramcode":"US19402600"}},
{"type":"Feature","geometry":{"type":"Point","coordinates":[-78.660593,35.714307]},"properties":{"educationprogramcode":"US19402600"}},
{"type":"Feature","geometry":{"type":"Point","coordinates":[-78.660593,35.714307]},"properties":{"educationprogramcode":"US19402600"}},
{"type":"Feature","geometry":{"type":"Point","coordinates":[-78.660593,35.714307]},"properties":{"educationprogramcode":"US19402600"}},
{"type":"Feature","geometry":{"type":"Point","coordinates":[-78.660593,35.714307]},"properties":{"educationprogramcode":"US19402600"}},
{"type":"Feature","geometry":{"type":"Point","coordinates":[-78.660593,35.714307]},"properties":{"educationprogramcode":"US19402600"}},
{"type":"Feature","geometry":{"type":"Point","coordinates":[-78.660593,35.714307]},"properties":{"educationprogramcode":"US19402600"}},
{"type":"Feature","geometry":{"type":"Point","coordinates":[-78.660593,35.714307]},"properties":{"educationprogramcode":"US19402600"}},
{"type":"Feature","geometry":{"type":"Point","coordinates":[-78.5319,35.86662]},"properties":{"educationprogramcode":"US19402600"}},
{"type":"Feature","geometry":{"type":"Point","coordinates":[-78.697656,35.804021]},"properties":{"educationprogramcode":"US19402600"}},
{"type":"Feature","geometry":{"type":"Point","coordinates":[-78.697656,35.804021]},"properties":{"educationprogramcode":"US19402600"}},
{"type":"Feature","geometry":{"type":"Point","coordinates":[-78.697656,35.804021]},"properties":{"educationprogramcode":"US19402600"}},
{"type":"Feature","geometry":{"type":"Point","coordinates":[-78.697656,35.804021]},"properties":{"educationprogramcode":"US19402600"}},
{"type":"Feature","geometry":{"type":"Point","coordinates":[-78.697656,35.804021]},"properties":{"educationprogramcode":"US19402600"}},
{"type":"Feature","geometry":{"type":"Point","coordinates":[-78.697656,35.804021]},"properties":{"educationprogramcode":"US19402600"}},
{"type":"Feature","geometry":{"type":"Point","coordinates":[-78.697656,35.804021]},"properties":{"educationprogramcode":"US19402600"}},
{"type":"Feature","geometry":{"type":"Point","coordinates":[-78.697656,35.804021]},"properties":{"educationprogramcode":"US19402600"}},
{"type":"Feature","geometry":{"type":"Point","coordinates":[-78.697656,35.804021]},"properties":{"educationprogramcode":"US19402600"}},
{"type":"Feature","geometry":{"type":"Point","coordinates":[-78.697656,35.804021]},"properties":{"educationprogramcode":"US19402600"}},
{"type":"Feature","geometry":{"type":"Point","coordinates":[-78.697656,35.804021]},"properties":{"educationprogramcode":"US19402600"}},
{"type":"Feature","geometry":{"type":"Point","coordinates":[-78.697656,35.804021]},"properties":{"educationprogramcode":"US19402600"}},
{"type":"Feature","geometry":{"type":"Point","coordinates":[-78.697656,35.804021]},"properties":{"educationprogramcode":"US19402600"}},
{"type":"Feature","geometry":{"type":"Point","coordinates":[-78.697656,35.804021]},"properties":{"educationprogramcode":"US19402600"}},
{"type":"Feature","geometry":{"type":"Point","coordinates":[-78.697656,35.804021]},"properties":{"educationprogramcode":"US19402600"}},
{"type":"Feature","geometry":{"type":"Point","coordinates":[-78.697656,35.804021]},"properties":{"educationprogramcode":"US19402600"}},
{"type":"Feature","geometry":{"type":"Point","coordinates":[-78.697656,35.804021]},"properties":{"educationprogramcode":"US19402600"}},
{"type":"Feature","geometry":{"type":"Point","coordinates":[-78.697656,35.804021]},"properties":{"educationprogramcode":"US19402600"}},
{"type":"Feature","geometry":{"type":"Point","coordinates":[-78.697656,35.804021]},"properties":{"educationprogramcode":"US19402600"}},
{"type":"Feature","geometry":{"type":"Point","coordinates":[-78.63252,35.84172]},"properties":{"educationprogramcode":"US19402600"}},
{"type":"Feature","geometry":{"type":"Point","coordinates":[-78.63252,35.84172]},"properties":{"educationprogramcode":"US19402600"}},
{"type":"Feature","geometry":{"type":"Point","coordinates":[-78.63252,35.84172]},"properties":{"educationprogramcode":"US19402600"}},
{"type":"Feature","geometry":{"type":"Point","coordinates":[-78.63252,35.84172]},"properties":{"educationprogramcode":"US19402600"}},
{"type":"Feature","geometry":{"type":"Point","coordinates":[-78.63252,35.84172]},"properties":{"educationprogramcode":"US19402600"}},
{"type":"Feature","geometry":{"type":"Point","coordinates":[-78.63252,35.84172]},"properties":{"educationprogramcode":"US19402600"}},
{"type":"Feature","geometry":{"type":"Point","coordinates":[-78.63252,35.84172]},"properties":{"educationprogramcode":"US19402600"}},
{"type":"Feature","geometry":{"type":"Point","coordinates":[-78.63252,35.84172]},"properties":{"educationprogramcode":"US19402600"}},
{"type":"Feature","geometry":{"type":"Point","coordinates":[-78.63252,35.84172]},"properties":{"educationprogramcode":"US19402600"}},
{"type":"Feature","geometry":{"type":"Point","coordinates":[-78.63252,35.84172]},"properties":{"educationprogramcode":"US19402600"}},
{"type":"Feature","geometry":{"type":"Point","coordinates":[-78.63252,35.84172]},"properties":{"educationprogramcode":"US19402600"}},
{"type":"Feature","geometry":{"type":"Point","coordinates":[-78.63252,35.84172]},"properties":{"educationprogramcode":"US19402600"}},
{"type":"Feature","geometry":{"type":"Point","coordinates":[-78.63252,35.84172]},"properties":{"educationprogramcode":"US19402600"}},
{"type":"Feature","geometry":{"type":"Point","coordinates":[-78.583787,35.761643]},"properties":{"educationprogramcode":"US19402600"}},
{"type":"Feature","geometry":{"type":"Point","coordinates":[-78.583787,35.761643]},"properties":{"educationprogramcode":"US19402600"}},
{"type":"Feature","geometry":{"type":"Point","coordinates":[-78.583787,35.761643]},"properties":{"educationprogramcode":"US19402600"}},
{"type":"Feature","geometry":{"type":"Point","coordinates":[-78.583787,35.761643]},"properties":{"educationprogramcode":"US19402600"}},
{"type":"Feature","geometry":{"type":"Point","coordinates":[-78.583787,35.761643]},"properties":{"educationprogramcode":"US19402600"}},
{"type":"Feature","geometry":{"type":"Point","coordinates":[-78.583787,35.761643]},"properties":{"educationprogramcode":"US19402600"}},
{"type":"Feature","geometry":{"type":"Point","coordinates":[-78.583787,35.761643]},"properties":{"educationprogramcode":"US19402600"}},
{"type":"Feature","geometry":{"type":"Point","coordinates":[-78.583787,35.761643]},"properties":{"educationprogramcode":"US19402600"}},
{"type":"Feature","geometry":{"type":"Point","coordinates":[-78.583787,35.761643]},"properties":{"educationprogramcode":"US19402600"}},
{"type":"Feature","geometry":{"type":"Point","coordinates":[-78.583787,35.761643]},"properties":{"educationprogramcode":"US19402600"}},
{"type":"Feature","geometry":{"type":"Point","coordinates":[-78.583787,35.761643]},"properties":{"educationprogramcode":"US19402600"}},
{"type":"Feature","geometry":{"type":"Point","coordinates":[-78.583787,35.761643]},"properties":{"educationprogramcode":"US19402600"}},
{"type":"Feature","geometry":{"type":"Point","coordinates":[-78.583787,35.761643]},"properties":{"educationprogramcode":"US19402600"}},
{"type":"Feature","geometry":{"type":"Point","coordinates":[-78.583787,35.761643]},"properties":{"educationprogramcode":"US19402600"}},
{"type":"Feature","geometry":{"type":"Point","coordinates":[-78.583787,35.761643]},"properties":{"educationprogramcode":"US19402600"}},
{"type":"Feature","geometry":{"type":"Point","coordinates":[-78.583787,35.761643]},"properties":{"educationprogramcode":"US19402600"}},
{"type":"Feature","geometry":{"type":"Point","coordinates":[-78.583787,35.761643]},"properties":{"educationprogramcode":"US19402600"}},
{"type":"Feature","geometry":{"type":"Point","coordinates":[-78.583787,35.761643]},"properties":{"educationprogramcode":"US19402600"}},
{"type":"Feature","geometry":{"type":"Point","coordinates":[-78.583787,35.761643]},"properties":{"educationprogramcode":"US19402600"}},
{"type":"Feature","geometry":{"type":"Point","coordinates":[-78.583787,35.761643]},"properties":{"educationprogramcode":"US19402600"}},
{"type":"Feature","geometry":{"type":"Point","coordinates":[-78.583787,35.761643]},"properties":{"educationprogramcode":"US19402600"}},
{"type":"Feature","geometry":{"type":"Point","coordinates":[-78.583787,35.761643]},"properties":{"educationprogramcode":"US19402600"}},
{"type":"Feature","geometry":{"type":"Point","coordinates":[-78.583787,35.761643]},"properties":{"educationprogramcode":"US19402600"}},
{"type":"Feature","geometry":{"type":"Point","coordinates":[-78.583787,35.761643]},"properties":{"educationprogramcode":"US19402600"}},
{"type":"Feature","geometry":{"type":"Point","coordinates":[-78.583787,35.761643]},"properties":{"educationprogramcode":"US19402600"}},
{"type":"Feature","geometry":{"type":"Point","coordinates":[-78.583787,35.761643]},"properties":{"educationprogramcode":"US19402600"}},
{"type":"Feature","geometry":{"type":"Point","coordinates":[-78.583787,35.761643]},"properties":{"educationprogramcode":"US19402600"}},
{"type":"Feature","geometry":{"type":"Point","coordinates":[-78.583787,35.761643]},"properties":{"educationprogramcode":"US19402600"}},
{"type":"Feature","geometry":{"type":"Point","coordinates":[-78.583787,35.761643]},"properties":{"educationprogramcode":"US19402600"}},
{"type":"Feature","geometry":{"type":"Point","coordinates":[-78.583787,35.761643]},"properties":{"educationprogramcode":"US19402600"}},
{"type":"Feature","geometry":{"type":"Point","coordinates":[-78.583787,35.761643]},"properties":{"educationprogramcode":"US19402600"}},
{"type":"Feature","geometry":{"type":"Point","coordinates":[-78.583787,35.761643]},"properties":{"educationprogramcode":"US19402600"}},
{"type":"Feature","geometry":{"type":"Point","coordinates":[-78.583787,35.761643]},"properties":{"educationprogramcode":"US19402600"}},
{"type":"Feature","geometry":{"type":"Point","coordinates":[-78.583787,35.761643]},"properties":{"educationprogramcode":"US19402600"}},
{"type":"Feature","geometry":{"type":"Point","coordinates":[-78.583787,35.761643]},"properties":{"educationprogramcode":"US19402600"}},
{"type":"Feature","geometry":{"type":"Point","coordinates":[-78.583787,35.761643]},"properties":{"educationprogramcode":"US19402600"}},
{"type":"Feature","geometry":{"type":"Point","coordinates":[-78.583787,35.761643]},"properties":{"educationprogramcode":"US19402600"}},
{"type":"Feature","geometry":{"type":"Point","coordinates":[-78.583787,35.761643]},"properties":{"educationprogramcode":"US19402600"}},
{"type":"Feature","geometry":{"type":"Point","coordinates":[-78.689606,35.856914]},"properties":{"educationprogramcode":"US19402600"}},
{"type":"Feature","geometry":{"type":"Point","coordinates":[-78.689606,35.856914]},"properties":{"educationprogramcode":"US19402600"}},
{"type":"Feature","geometry":{"type":"Point","coordinates":[-78.707118,35.902051]},"properties":{"educationprogramcode":"US19402600"}},
{"type":"Feature","geometry":{"type":"Point","coordinates":[-78.707118,35.902051]},"properties":{"educationprogramcode":"US19402600"}},
{"type":"Feature","geometry":{"type":"Point","coordinates":[-78.637839,35.889314]},"properties":{"educationprogramcode":"US19402600"}},
{"type":"Feature","geometry":{"type":"Point","coordinates":[-78.637839,35.889314]},"properties":{"educationprogramcode":"US19402600"}},
{"type":"Feature","geometry":{"type":"Point","coordinates":[-78.637839,35.889314]},"properties":{"educationprogramcode":"US19402600"}},
{"type":"Feature","geometry":{"type":"Point","coordinates":[-78.535615,35.863033]},"properties":{"educationprogramcode":"US19402600"}},
{"type":"Feature","geometry":{"type":"Point","coordinates":[-78.535615,35.863033]},"properties":{"educationprogramcode":"US19402600"}},
{"type":"Feature","geometry":{"type":"Point","coordinates":[-78.535615,35.863033]},"properties":{"educationprogramcode":"US19402600"}},
{"type":"Feature","geometry":{"type":"Point","coordinates":[-78.743481,35.877636]},"properties":{"educationprogramcode":"US19402600"}},
{"type":"Feature","geometry":{"type":"Point","coordinates":[-78.572747,35.819644]},"properties":{"educationprogramcode":"US19402600"}},
{"type":"Feature","geometry":{"type":"Point","coordinates":[-78.869276,36.034161]},"properties":{"educationprogramcode":"US19402600"}},
{"type":"Feature","geometry":{"type":"Point","coordinates":[-78.869276,36.034161]},"properties":{"educationprogramcode":"US19402600"}},
{"type":"Feature","geometry":{"type":"Point","coordinates":[-78.869276,36.034161]},"properties":{"educationprogramcode":"US19402600"}},
{"type":"Feature","geometry":{"type":"Point","coordinates":[-78.869276,36.034161]},"properties":{"educationprogramcode":"US19402600"}},
{"type":"Feature","geometry":{"type":"Point","coordinates":[-78.948419,36.017812]},"properties":{"educationprogramcode":"US19402600"}},
{"type":"Feature","geometry":{"type":"Point","coordinates":[-78.940527,35.964557]},"properties":{"educationprogramcode":"US19402600"}},
{"type":"Feature","geometry":{"type":"Point","coordinates":[-78.938612,35.997189]},"properties":{"educationprogramcode":"US19402600"}},
{"type":"Feature","geometry":{"type":"Point","coordinates":[-78.940724,36.001767]},"properties":{"educationprogramcode":"US19402600"}},
{"type":"Feature","geometry":{"type":"Point","coordinates":[-78.940724,36.001767]},"properties":{"educationprogramcode":"US19402600"}},
{"type":"Feature","geometry":{"type":"Point","coordinates":[-78.940724,36.001767]},"properties":{"educationprogramcode":"US19402600"}},
{"type":"Feature","geometry":{"type":"Point","coordinates":[-78.917612,35.916567]},"properties":{"educationprogramcode":"US19402600"}},
{"type":"Feature","geometry":{"type":"Point","coordinates":[-77.831514,35.974314]},"properties":{"educationprogramcode":"US19402600"}},
{"type":"Feature","geometry":{"type":"Point","coordinates":[-77.831514,35.974314]},"properties":{"educationprogramcode":"US19402600"}},
{"type":"Feature","geometry":{"type":"Point","coordinates":[-77.96502,35.54286]},"properties":{"educationprogramcode":"US19402600"}},
{"type":"Feature","geometry":{"type":"Point","coordinates":[-77.96502,35.54286]},"properties":{"educationprogramcode":"US19402600"}},
{"type":"Feature","geometry":{"type":"Point","coordinates":[-77.43858,35.62638]},"properties":{"educationprogramcode":"US19402600"}},
{"type":"Feature","geometry":{"type":"Point","coordinates":[-77.43858,35.62638]},"properties":{"educationprogramcode":"US19402600"}},
{"type":"Feature","geometry":{"type":"Point","coordinates":[-77.43858,35.62638]},"properties":{"educationprogramcode":"US19402600"}},
{"type":"Feature","geometry":{"type":"Point","coordinates":[-77.371771,35.607]},"properties":{"educationprogramcode":"US19402600"}},
{"type":"Feature","geometry":{"type":"Point","coordinates":[-78.012797,35.634649]},"properties":{"educationprogramcode":"US19402600"}},
{"type":"Feature","geometry":{"type":"Point","coordinates":[-77.9833,35.492476]},"properties":{"educationprogramcode":"US19402600"}},
{"type":"Feature","geometry":{"type":"Point","coordinates":[-77.9833,35.492476]},"properties":{"educationprogramcode":"US19402600"}},
{"type":"Feature","geometry":{"type":"Point","coordinates":[-78.100591,35.734926]},"properties":{"educationprogramcode":"US19402600"}},
{"type":"Feature","geometry":{"type":"Point","coordinates":[-77.704479,35.581146]},"properties":{"educationprogramcode":"US19402600"}},
{"type":"Feature","geometry":{"type":"Point","coordinates":[-77.920181,35.73252]},"properties":{"educationprogramcode":"US19402600"}},
{"type":"Feature","geometry":{"type":"Point","coordinates":[-77.920181,35.73252]},"properties":{"educationprogramcode":"US19402600"}},
{"type":"Feature","geometry":{"type":"Point","coordinates":[-77.920181,35.73252]},"properties":{"educationprogramcode":"US19402600"}},
{"type":"Feature","geometry":{"type":"Point","coordinates":[-77.920181,35.73252]},"properties":{"educationprogramcode":"US19402600"}},
{"type":"Feature","geometry":{"type":"Point","coordinates":[-77.920181,35.73252]},"properties":{"educationprogramcode":"US19402600"}},
{"type":"Feature","geometry":{"type":"Point","coordinates":[-77.920181,35.73252]},"properties":{"educationprogramcode":"US19402600"}},
{"type":"Feature","geometry":{"type":"Point","coordinates":[-77.944711,35.75562]},"properties":{"educationprogramcode":"US19402600"}},
{"type":"Feature","geometry":{"type":"Point","coordinates":[-77.944711,35.75562]},"properties":{"educationprogramcode":"US19402600"}},
{"type":"Feature","geometry":{"type":"Point","coordinates":[-80.960674,35.269641]},"properties":{"educationprogramcode":"US19402600"}},
{"type":"Feature","geometry":{"type":"Point","coordinates":[-78.864925,35.064922]},"properties":{"educationprogramcode":"US19402600"}},
{"type":"Feature","geometry":{"type":"Point","coordinates":[-78.962365,35.081833]},"properties":{"educationprogramcode":"US19402600"}},
{"type":"Feature","geometry":{"type":"Point","coordinates":[-78.970982,35.029744]},"properties":{"educationprogramcode":"US19402600"}},
{"type":"Feature","geometry":{"type":"Point","coordinates":[-78.970982,35.029744]},"properties":{"educationprogramcode":"US19402600"}},
{"type":"Feature","geometry":{"type":"Point","coordinates":[-78.970982,35.029744]},"properties":{"educationprogramcode":"US19402600"}},
{"type":"Feature","geometry":{"type":"Point","coordinates":[-78.970982,35.029744]},"properties":{"educationprogramcode":"US19402600"}},
{"type":"Feature","geometry":{"type":"Point","coordinates":[-78.970982,35.029744]},"properties":{"educationprogramcode":"US19402600"}},
{"type":"Feature","geometry":{"type":"Point","coordinates":[-78.970982,35.029744]},"properties":{"educationprogramcode":"US19402600"}},
{"type":"Feature","geometry":{"type":"Point","coordinates":[-78.897217,35.128576]},"properties":{"educationprogramcode":"US19402600"}},
{"type":"Feature","geometry":{"type":"Point","coordinates":[-79.003491,35.05772]},"properties":{"educationprogramcode":"US19402600"}},
{"type":"Feature","geometry":{"type":"Point","coordinates":[-78.339145,35.000598]},"properties":{"educationprogramcode":"US19402600"}},
{"type":"Feature","geometry":{"type":"Point","coordinates":[-78.339145,35.000598]},"properties":{"educationprogramcode":"US19402600"}},
{"type":"Feature","geometry":{"type":"Point","coordinates":[-78.339145,35.000598]},"properties":{"educationprogramcode":"US19402600"}},
{"type":"Feature","geometry":{"type":"Point","coordinates":[-78.619199,35.310491]},"properties":{"educationprogramcode":"US19402600"}},
{"type":"Feature","geometry":{"type":"Point","coordinates":[-78.619199,35.310491]},"properties":{"educationprogramcode":"US19402600"}},
{"type":"Feature","geometry":{"type":"Point","coordinates":[-78.619199,35.310491]},"properties":{"educationprogramcode":"US19402600"}},
{"type":"Feature","geometry":{"type":"Point","coordinates":[-78.619199,35.310491]},"properties":{"educationprogramcode":"US19402600"}},
{"type":"Feature","geometry":{"type":"Point","coordinates":[-78.619199,35.310491]},"properties":{"educationprogramcode":"US19402600"}},
{"type":"Feature","geometry":{"type":"Point","coordinates":[-78.619199,35.310491]},"properties":{"educationprogramcode":"US19402600"}},
{"type":"Feature","geometry":{"type":"Point","coordinates":[-78.619199,35.310491]},"properties":{"educationprogramcode":"US19402600"}},
{"type":"Feature","geometry":{"type":"Point","coordinates":[-78.619199,35.310491]},"properties":{"educationprogramcode":"US19402600"}},
{"type":"Feature","geometry":{"type":"Point","coordinates":[-78.619199,35.310491]},"properties":{"educationprogramcode":"US19402600"}},
{"type":"Feature","geometry":{"type":"Point","coordinates":[-78.619199,35.310491]},"properties":{"educationprogramcode":"US19402600"}},
{"type":"Feature","geometry":{"type":"Point","coordinates":[-78.619199,35.310491]},"properties":{"educationprogramcode":"US19402600"}},
{"type":"Feature","geometry":{"type":"Point","coordinates":[-78.619199,35.310491]},"properties":{"educationprogramcode":"US19402600"}},
{"type":"Feature","geometry":{"type":"Point","coordinates":[-78.619199,35.310491]},"properties":{"educationprogramcode":"US19402600"}},
{"type":"Feature","geometry":{"type":"Point","coordinates":[-78.619199,35.310491]},"properties":{"educationprogramcode":"US19402600"}},
{"type":"Feature","geometry":{"type":"Point","coordinates":[-78.619199,35.310491]},"properties":{"educationprogramcode":"US19402600"}},
{"type":"Feature","geometry":{"type":"Point","coordinates":[-78.619199,35.310491]},"properties":{"educationprogramcode":"US19402600"}},
{"type":"Feature","geometry":{"type":"Point","coordinates":[-78.619199,35.310491]},"properties":{"educationprogramcode":"US19402600"}},
{"type":"Feature","geometry":{"type":"Point","coordinates":[-78.619199,35.310491]},"properties":{"educationprogramcode":"US19402600"}},
{"type":"Feature","geometry":{"type":"Point","coordinates":[-78.619199,35.310491]},"properties":{"educationprogramcode":"US19402600"}},
{"type":"Feature","geometry":{"type":"Point","coordinates":[-78.619199,35.310491]},"properties":{"educationprogramcode":"US19402600"}},
{"type":"Feature","geometry":{"type":"Point","coordinates":[-78.608202,35.3097]},"properties":{"educationprogramcode":"US19402600"}},
{"type":"Feature","geometry":{"type":"Point","coordinates":[-78.608202,35.3097]},"properties":{"educationprogramcode":"US19402600"}},
{"type":"Feature","geometry":{"type":"Point","coordinates":[-78.608202,35.3097]},"properties":{"educationprogramcode":"US19402600"}},
{"type":"Feature","geometry":{"type":"Point","coordinates":[-78.673753,35.327232]},"properties":{"educationprogramcode":"US19402600"}},
{"type":"Feature","geometry":{"type":"Point","coordinates":[-78.673753,35.327232]},"properties":{"educationprogramcode":"US19402600"}},
{"type":"Feature","geometry":{"type":"Point","coordinates":[-77.960596,34.962078]},"properties":{"educationprogramcode":"US19402600"}},
{"type":"Feature","geometry":{"type":"Point","coordinates":[-78.797717,35.231971]},"properties":{"educationprogramcode":"US19402600"}},
{"type":"Feature","geometry":{"type":"Point","coordinates":[-78.066179,35.197486]},"properties":{"educationprogramcode":"US19402600"}},
{"type":"Feature","geometry":{"type":"Point","coordinates":[-78.066179,35.197486]},"properties":{"educationprogramcode":"US19402600"}},
{"type":"Feature","geometry":{"type":"Point","coordinates":[-78.066179,35.197486]},"properties":{"educationprogramcode":"US19402600"}},
{"type":"Feature","geometry":{"type":"Point","coordinates":[-78.066179,35.197486]},"properties":{"educationprogramcode":"US19402600"}},
{"type":"Feature","geometry":{"type":"Point","coordinates":[-78.501727,35.017786]},"properties":{"educationprogramcode":"US19402600"}},
{"type":"Feature","geometry":{"type":"Point","coordinates":[-78.501727,35.017786]},"properties":{"educationprogramcode":"US19402600"}},
{"type":"Feature","geometry":{"type":"Point","coordinates":[-79.194731,34.682421]},"properties":{"educationprogramcode":"US19402600"}},
{"type":"Feature","geometry":{"type":"Point","coordinates":[-78.976743,35.175116]},"properties":{"educationprogramcode":"US19402600"}},
{"type":"Feature","geometry":{"type":"Point","coordinates":[-77.915225,34.142287]},"properties":{"educationprogramcode":"US19402600"}},
{"type":"Feature","geometry":{"type":"Point","coordinates":[-77.077035,35.101125]},"properties":{"educationprogramcode":"US19402600"}}
]}